{
  "last_updated": "2026-07-15T10:41:01.929979+00:00",
  "fixed_total": 14,
  "fixed_working": 6,
  "dynamic_total": 8,
  "dynamic_working": 8,
  "fixed_channels": [
    {
      "canonical": "Star Jalsha",
      "display_name": "Star Jalsha",
      "logo_url": "https://iptv-org.github.io/iptv/logos/StarJalsha.png",
      "category": "entertainment",
      "language": [
        "Bengali"
      ],
      "position": 1,
      "tier": "SILVER",
      "status": "online",
      "stream_count": 1,
      "streams": [
        {
          "url": "http://premiumtvs.space/live/1Aoen7elp5/IgMJ60tmAa/8540.ts",
          "tier": "SILVER",
          "score": 71.32,
          "ttfb_ms": 855.79,
          "speed_kbps": 4.67,
          "is_primary": true
        }
      ]
    },
    {
      "canonical": "Jalsha Movies",
      "display_name": "Jalsha Movies",
      "logo_url": "https://iptv-org.github.io/iptv/logos/JalshaMovies.png",
      "category": "entertainment",
      "language": [
        "Bengali"
      ],
      "position": 2,
      "tier": "OFFLINE",
      "status": "offline",
      "stream_count": 0,
      "streams": []
    },
    {
      "canonical": "Zee Bangla",
      "display_name": "Zee Bangla",
      "logo_url": "https://iptv-org.github.io/iptv/logos/ZeeBangla.png",
      "category": "entertainment",
      "language": [
        "Bengali"
      ],
      "position": 3,
      "tier": "SILVER",
      "status": "online",
      "stream_count": 2,
      "streams": [
        {
          "url": "https://d1g8wgjurz8via.cloudfront.net/bpk-tv/ColorsHD/default/ColorsHD.m3u8",
          "tier": "SILVER",
          "score": 193.4,
          "ttfb_ms": 99.01,
          "speed_kbps": 16.92,
          "is_primary": true
        },
        {
          "url": "https://d1g8wgjurz8via.cloudfront.net/bpk-tv/ColorsHD/default/ColorsHD-video=2137600.m3u8",
          "tier": "SILVER",
          "score": 51.04,
          "ttfb_ms": 872.24,
          "speed_kbps": 0.84,
          "is_primary": false
        }
      ]
    },
    {
      "canonical": "Zee Bangla Sonar",
      "display_name": "Zee Bangla Sonar",
      "logo_url": "",
      "category": "entertainment",
      "language": [
        "Bengali"
      ],
      "position": 4,
      "tier": "OFFLINE",
      "status": "offline",
      "stream_count": 0,
      "streams": []
    },
    {
      "canonical": "Sony Aath",
      "display_name": "Sony Aath",
      "logo_url": "https://iptv-org.github.io/iptv/logos/SonyAath.png",
      "category": "entertainment",
      "language": [
        "Bengali"
      ],
      "position": 5,
      "tier": "OFFLINE",
      "status": "offline",
      "stream_count": 0,
      "streams": []
    },
    {
      "canonical": "Duronto TV",
      "display_name": "Duronto TV",
      "logo_url": "https://iptv-org.github.io/iptv/logos/DurontoTV.png",
      "category": "kids",
      "language": [
        "Bengali"
      ],
      "position": 6,
      "tier": "OFFLINE",
      "status": "offline",
      "stream_count": 0,
      "streams": []
    },
    {
      "canonical": "Somoy TV",
      "display_name": "Somoy TV",
      "logo_url": "https://iptv-org.github.io/iptv/logos/SomoyNewsTV.png",
      "category": "news",
      "language": [
        "Bengali"
      ],
      "position": 7,
      "tier": "OFFLINE",
      "status": "offline",
      "stream_count": 0,
      "streams": []
    },
    {
      "canonical": "Jamuna TV",
      "display_name": "Jamuna TV",
      "logo_url": "https://iptv-org.github.io/iptv/logos/JamunaTV.png",
      "category": "news",
      "language": [
        "Bengali"
      ],
      "position": 8,
      "tier": "GOLD",
      "status": "online",
      "stream_count": 1,
      "streams": [
        {
          "url": "https://bozztv.com/rongo/rongo-JamunaTelevision/index.m3u8",
          "tier": "GOLD",
          "score": 97.73,
          "ttfb_ms": 277.68,
          "speed_kbps": 1.25,
          "is_primary": true
        }
      ]
    },
    {
      "canonical": "NTV News",
      "display_name": "NTV News",
      "logo_url": "https://iptv-org.github.io/iptv/logos/NTVBangladesh.png",
      "category": "news",
      "language": [
        "Bengali"
      ],
      "position": 9,
      "tier": "OFFLINE",
      "status": "offline",
      "stream_count": 0,
      "streams": []
    },
    {
      "canonical": "T Sports HD",
      "display_name": "T Sports HD",
      "logo_url": "https://iptv-org.github.io/iptv/logos/TSports.png",
      "category": "sports",
      "language": [
        "Bengali",
        "English"
      ],
      "position": 10,
      "tier": "GOLD",
      "status": "online",
      "stream_count": 1,
      "streams": [
        {
          "url": "http://114.130.57.233:8080/LIVE-Sports/video.m3u8?token=SkQuhAXZxgBan1",
          "tier": "GOLD",
          "score": 79.7,
          "ttfb_ms": 921.63,
          "speed_kbps": 0.23,
          "is_primary": true
        }
      ]
    },
    {
      "canonical": "Nickelodeon",
      "display_name": "Nickelodeon",
      "logo_url": "https://iptv-org.github.io/iptv/logos/Nickelodeon.png",
      "category": "kids",
      "language": [
        "Bengali",
        "English"
      ],
      "position": 11,
      "tier": "SILVER",
      "status": "online",
      "stream_count": 3,
      "streams": [
        {
          "url": "https://jmp2.uk/plu-6824ce10c5d53e1351ceb8d1.m3u8",
          "tier": "SILVER",
          "score": 116.81,
          "ttfb_ms": 446.37,
          "speed_kbps": 7.31,
          "is_primary": true
        },
        {
          "url": "http://151.80.18.177:86/Nickelodeon_Junior/index.m3u8",
          "tier": "SILVER",
          "score": 93.25,
          "ttfb_ms": 296.46,
          "speed_kbps": 0.6,
          "is_primary": false
        },
        {
          "url": "http://151.80.18.177:86/Nickelodeon_FR/index.m3u8",
          "tier": "GOLD",
          "score": 82.77,
          "ttfb_ms": 438.61,
          "speed_kbps": 0.4,
          "is_primary": false
        }
      ]
    },
    {
      "canonical": "Sony YAY!",
      "display_name": "Sony YAY!",
      "logo_url": "https://iptv-org.github.io/iptv/logos/SonyYAY.png",
      "category": "kids",
      "language": [
        "Bengali",
        "English"
      ],
      "position": 12,
      "tier": "OFFLINE",
      "status": "offline",
      "stream_count": 0,
      "streams": []
    },
    {
      "canonical": "Sonic",
      "display_name": "Sonic",
      "logo_url": "https://iptv-org.github.io/iptv/logos/Sonic.png",
      "category": "kids",
      "language": [
        "Bengali",
        "English",
        "Hindi"
      ],
      "position": 13,
      "tier": "SILVER",
      "status": "online",
      "stream_count": 1,
      "streams": [
        {
          "url": "https://stream-us-east-1.getpublica.com/playlist.m3u8?network_id=16764",
          "tier": "SILVER",
          "score": 89.9,
          "ttfb_ms": 448.32,
          "speed_kbps": 2.96,
          "is_primary": true
        }
      ]
    },
    {
      "canonical": "Sony BBC Earth",
      "display_name": "Sony BBC Earth",
      "logo_url": "https://iptv-org.github.io/iptv/logos/SonyBBCEarth.png",
      "category": "entertainment",
      "language": [
        "English"
      ],
      "position": 14,
      "tier": "OFFLINE",
      "status": "offline",
      "stream_count": 0,
      "streams": []
    }
  ],
  "dynamic_channels": [
    {
      "canonical": "Akash Aath",
      "display_name": "Akash Aath",
      "logo_url": "",
      "category": "entertainment",
      "language": [
        "Bengali"
      ],
      "tier": "DYNAMIC",
      "status": "online",
      "stream_count": 1,
      "streams": [
        {
          "url": "https://live.thebosstv.com:30443/dwlive/AAKAASH-AATH/chunks.m3u8",
          "tier": "DYNAMIC",
          "score": 41.25,
          "ttfb_ms": 1544.96,
          "speed_kbps": 0.25,
          "is_primary": true
        }
      ]
    },
    {
      "canonical": "Bangla TV",
      "display_name": "Bangla TV",
      "logo_url": "",
      "category": "entertainment",
      "language": [
        "Bengali"
      ],
      "tier": "DYNAMIC",
      "status": "online",
      "stream_count": 2,
      "streams": [
        {
          "url": "https://cdn-4.pishow.tv/live/1499/master.m3u8",
          "tier": "DYNAMIC",
          "score": 90.29,
          "ttfb_ms": 924.9,
          "speed_kbps": 0.39,
          "is_primary": true
        },
        {
          "url": "http://103.190.133.68:1935/news21live/live/playlist.m3u8",
          "tier": "DYNAMIC",
          "score": 43.24,
          "ttfb_ms": 1011.56,
          "speed_kbps": 0.14,
          "is_primary": false
        }
      ]
    },
    {
      "canonical": "Boishakhi TV",
      "display_name": "Boishakhi TV",
      "logo_url": "",
      "category": "entertainment",
      "language": [
        "Bengali"
      ],
      "tier": "DYNAMIC",
      "status": "online",
      "stream_count": 1,
      "streams": [
        {
          "url": "https://boishakhi.sonarbanglatv.com/boishakhi/boishakhitv/index.m3u8",
          "tier": "DYNAMIC",
          "score": 111.45,
          "ttfb_ms": 479.81,
          "speed_kbps": 0.69,
          "is_primary": true
        }
      ]
    },
    {
      "canonical": "Disney Channel",
      "display_name": "Disney Channel",
      "logo_url": "",
      "category": "kids",
      "language": [
        "English"
      ],
      "tier": "DYNAMIC",
      "status": "online",
      "stream_count": 1,
      "streams": [
        {
          "url": "http://88.212.15.19/live/test_disney/playlist.m3u8",
          "tier": "DYNAMIC",
          "score": 83.61,
          "ttfb_ms": 463.19,
          "speed_kbps": 0.9,
          "is_primary": true
        }
      ]
    },
    {
      "canonical": "HBO",
      "display_name": "HBO",
      "logo_url": "",
      "category": "movies",
      "language": [
        "English"
      ],
      "tier": "DYNAMIC",
      "status": "online",
      "stream_count": 1,
      "streams": [
        {
          "url": "https://cdn-4.pishow.tv/live/1473/master.m3u8",
          "tier": "DYNAMIC",
          "score": 89.19,
          "ttfb_ms": 940.9,
          "speed_kbps": 0.38,
          "is_primary": true
        }
      ]
    },
    {
      "canonical": "Independent TV",
      "display_name": "Independent TV",
      "logo_url": "",
      "category": "news",
      "language": [
        "Bengali"
      ],
      "tier": "DYNAMIC",
      "status": "online",
      "stream_count": 1,
      "streams": [
        {
          "url": "https://bozztv.com/rongo/rongo-IndependentTV/index.m3u8",
          "tier": "DYNAMIC",
          "score": 111.84,
          "ttfb_ms": 170.46,
          "speed_kbps": 2.64,
          "is_primary": true
        }
      ]
    },
    {
      "canonical": "Star Movies",
      "display_name": "Star Movies",
      "logo_url": "",
      "category": "movies",
      "language": [
        "English"
      ],
      "tier": "DYNAMIC",
      "status": "online",
      "stream_count": 1,
      "streams": [
        {
          "url": "http://znty.dyndns.org:5010/hls/foxm.m3u8",
          "tier": "DYNAMIC",
          "score": 70.35,
          "ttfb_ms": 621.33,
          "speed_kbps": 0.36,
          "is_primary": true
        }
      ]
    },
    {
      "canonical": "Star Sports 1",
      "display_name": "Star Sports 1",
      "logo_url": "",
      "category": "sports",
      "language": [
        "English"
      ],
      "tier": "DYNAMIC",
      "status": "online",
      "stream_count": 3,
      "streams": [
        {
          "url": "http://103.253.18.58:8000/play/a00t",
          "tier": "DYNAMIC",
          "score": 22.17,
          "ttfb_ms": 1643.12,
          "speed_kbps": 2.43,
          "is_primary": true
        },
        {
          "url": "http://103.253.18.58:8000/play/a00m",
          "tier": "DYNAMIC",
          "score": 21.46,
          "ttfb_ms": 1745.57,
          "speed_kbps": 2.29,
          "is_primary": false
        },
        {
          "url": "http://103.253.18.58:8000/play/a03o",
          "tier": "DYNAMIC",
          "score": 14.47,
          "ttfb_ms": 4475.11,
          "speed_kbps": 0.89,
          "is_primary": false
        }
      ]
    }
  ]
}